LICENSE
MANIFEST.in
README.md
pyproject.toml
tests/__init__.py
tests/test_cli.py
tests/test_core.py
vcmcp/__init__.py
vcmcp/cli.py
vcmcp/core.py
vcmcp/mcp_server.py
vcmcp/server.py
vcmcp/tool.py
vcmcp.egg-info/PKG-INFO
vcmcp.egg-info/SOURCES.txt
vcmcp.egg-info/dependency_links.txt
vcmcp.egg-info/entry_points.txt
vcmcp.egg-info/requires.txt
vcmcp.egg-info/top_level.txt