Metadata-Version: 2.4
Name: vcmcp
Version: 0.1.1
Summary: Version Control Model Protocol - MCP for AI agent checkpoint tracking and restoration
Author: VCMCP Team
License-Expression: MIT
Classifier: Development Status :: 3 - Alpha
Classifier: Intended Audience :: Developers
Classifier: Programming Language :: Python :: 3
Classifier: Programming Language :: Python :: 3.8
Classifier: Topic :: Software Development :: Version Control
Requires-Python: >=3.8
License-File: LICENSE
Requires-Dist: click
Requires-Dist: colorama
Requires-Dist: pyyaml
Requires-Dist: fastapi>=0.104.0
Requires-Dist: uvicorn>=0.23.0
Requires-Dist: pydantic>=2.4.2
Requires-Dist: mcp>=1.20.0
Provides-Extra: dev
Requires-Dist: pytest>=7.0.0; extra == "dev"
Requires-Dist: pytest-cov>=4.0.0; extra == "dev"
Requires-Dist: black>=23.0.0; extra == "dev"
Requires-Dist: isort>=5.12.0; extra == "dev"
Requires-Dist: flake8>=6.0.0; extra == "dev"
Requires-Dist: mypy>=1.0.0; extra == "dev"
Requires-Dist: pre-commit>=3.0.0; extra == "dev"
Dynamic: license-file
